ivoy/__init__.py
ivoy/client.py
ivoy/exc.py
ivoy/types.py
ivoy/version.py
ivoy/resources/__init__.py
ivoy/resources/base.py
ivoy/resources/budget.py
ivoy/resources/carrier_location.py
ivoy/resources/order.py
ivoy/resources/order_sharing.py
ivoy/resources/package.py
ivoy/resources/waybill.py
tests/__init__.py
tests/conftest.py
tests/test_client.py
ivoy-0.4.5.dist-info/LICENSE
ivoy-0.4.5.dist-info/METADATA
ivoy-0.4.5.dist-info/WHEEL
ivoy-0.4.5.dist-info/top_level.txt
ivoy-0.4.5.dist-info/RECORD
